<?xml version="1.0" encoding="utf-8"?>
<!--
Project: Navrhněte a implementujte aplikaci pro hru Dáma,
         projekt pro předmět ICP
Date:    2013/03/25
Team:    Radek Ševčík <xsevci44@stud.fit.vutbr.cz>
         Zbyněk Malinkovič <xmalin22@stud.fit.vutbr.cz>
-->
<root xmlns="urn:cz-vutbr-fit:icp:x-dama">
    <turn white="a3-b4" black="f6-e5"/>
    <turn white="e3-f4" black="b6-a5"/>
    <turn white="b4-c5" black="d6xb4"/>
    <turn white="f4xd6" black="c7xe5"/>
    <turn white="c3-d4" black="e5xc3"/>
    <turn white="b2xd4" black="h6-g5"/>
    <turn white="f2-e3" black="e7-d6"/>
    <turn white="e1-f2" black="g5-h4"/>
    <turn white="e3-f4" black="g7-f6"/>
    <turn white="a1-b2" black="b4-a3"/>
    <turn white="d2-c3" black="a7-b6"/>
    <turn white="c3-b4" black="a5xc3xa1"/>
    <turn white="d4-e5" black="f6xd4"/>
    <turn white="f2-e3" black="d4xf2"/>
    <turn white="g1xe3" black="h4xf2"/>
    <turn white="h2-g3" black="a1-c3"/>
    <turn white="f4-g5" black="f2-e1"/>
    <turn white="g3-f4" black="h8-g7"/>
    <turn white="g5-h6" black="d6-c5"/>
    <turn white="c1-d2" black="c3-f6"/>
    <turn white="d2-c3" black="e1xb4"/>
    <turn white="f4-g5" black="f6xh4"/>
    <turn white="e3-f4" black="h4-g5"/>
    <turn white="f4-e5" black="g5-e7"/>
    <turn white="e5-d6" black="d8-c7"/>
</root>
